test.py
src/__init__.py
src/hwtest.py
tools/__init__.py
tools/hwtest.py
uppercut/__init__.py
uppercut/constants.py
uppercut/environment.py
uppercut/module.py
uppercut/sharedvars.py
uppercut-0.1.11.dist-info/LICENSE
uppercut-0.1.11.dist-info/METADATA
uppercut-0.1.11.dist-info/WHEEL
uppercut-0.1.11.dist-info/top_level.txt
uppercut-0.1.11.dist-info/RECORD
