Metadata-Version: 2.1
Name: uppercut
Version: 0.1.11
Summary: A library to handle common tasks for creating an Uppercut module in python.
Home-page: https://github.com/StephanAm/uppercut.python.tools
Author: Stephan Marais
Maintainer: Stephan Marais
License: UNKNOWN
Platform: UNKNOWN
Classifier: Programming Language :: Python :: 3.7
Requires-Dist: redis
